setup.py
uerrno.py
micropython_cpython_uerrno.egg-info/PKG-INFO
micropython_cpython_uerrno.egg-info/SOURCES.txt
micropython_cpython_uerrno.egg-info/dependency_links.txt
micropython_cpython_uerrno.egg-info/top_level.txt